niuke/VL5.v
// VL5 位拆分与运算
`timescale 1ns / 1ns

module data_cal (
    input        clk,
    input        rst,
    input [15:0] d,
    input [ 1:0] sel,

    output [4:0] out,
    output       validout
);
    //*************code***********//
    reg [15:0] d_tmp;
    reg [ 4:0] out_tmp;
    reg        validout_tmp;

    always @(posedge clk or negedge rst) begin
        if (!rst) begin
            d_tmp <= 0;
        end else if (!sel) begin
            d_tmp <= d;
        end
    end

    always @(posedge clk or negedge rst) begin
        if (!rst) begin
            out_tmp <= 0;
        end else begin
            case (sel)
                2'b00: out_tmp <= 0;
                2'b01: out_tmp <= d_tmp[3:0] + d_tmp[7:4];
                2'b10: out_tmp <= d_tmp[3:0] + d_tmp[11:8];
                2'b11: out_tmp <= d_tmp[3:0] + d_tmp[15:12];
            endcase
        end
    end

    always @(posedge clk or negedge rst) begin
        if (!rst) begin
            validout_tmp <= 0;
        end else begin
            case (sel)
                2'b00: validout_tmp <= 0;
                2'b01: validout_tmp <= 1;
                2'b10: validout_tmp <= 1;
                2'b11: validout_tmp <= 1;
            endcase
        end
    end

    assign out      = out_tmp;
    assign validout = validout_tmp;
    //*************code***********//
endmodule

niuke/test_module.v
`timescale 1ns / 1ps
`include "./VL5.v"
module test_module;

// sequence_detect Parameters
parameter PERIOD  = 10;


// sequence_detect Inputs
reg   clk                                  = 0 ;
reg   rst_n                                = 0 ;
reg   data                                 ;

// sequence_detect Outputs
wire  match                                ;
wire  not_match                            ;


initial
begin
    forever #(PERIOD/2)  clk=~clk;
end

initial
begin
    #(PERIOD*2) rst_n  =  1;
    data = 0;
    #PERIOD data = 1;
    #PERIOD data = 1;
    #PERIOD data = 1;
    #PERIOD data = 0;
    #PERIOD data = 0;

    #PERIOD data = 0;
    #PERIOD data = 1;
    #PERIOD data = 1;
    #PERIOD data = 1;
    #PERIOD data = 0;
    #PERIOD data = 0;

    #PERIOD data = 1;
    #PERIOD data = 0;
    #PERIOD data = 0;
    #PERIOD data = 0;
    #PERIOD data = 0;
    #PERIOD data = 0;
end

reg [15:0] d;
reg [1:0] sel;
initial begin
    #(PERIOD*2) rst_n  =  1;
    d = 16'h1234;
    sel = 2'd0;
    #PERIOD sel = 2'd1;
    #PERIOD sel = 2'd2;
    #PERIOD d = 16'h2345;
    sel = 2'd0;
    #PERIOD sel = 2'd1;
end

data_cal u_data_cal(
    .clk      (clk      ),
    .rst      (rst_n      ),
    .d        (d        ),
    .sel      (sel      ),
    .out      (      ),
    .validout ( )
);

////////////////////////////////////////////////////////////
    initial begin
        $dumpfile("wave.vcd");  //生成的vcd文件名称
        $dumpvars(0, test_module);  //tb模块名称
        #20000 $finish;
    end
////////////////////////////////////////////////////////////
endmodule

niuke/wave.vcd
$date
	Mon May 15 20:34:07 2023
$end
$version
	Icarus Verilog
$end
$timescale
	1ns
$end
$scope module test_module $end
$var reg 1 ! clk $end
$var reg 16 " d [15:0] $end
$var reg 1 # data $end
$var reg 1 $ rst_n $end
$var reg 2 % sel [1:0] $end
$scope module u_data_cal $end
$var wire 1 ! clk $end
$var wire 16 & d [15:0] $end
$var wire 5 ' out [4:0] $end
$var wire 1 $ rst $end
$var wire 2 ( sel [1:0] $end
$var wire 1 ) validout $end
$var reg 16 * d_tmp [15:0] $end
$var reg 5 + out_tmp [4:0] $end
$var reg 1 , validout_tmp $end
$upscope $end
$upscope $end
$enddefinitions $end
#0
$dumpvars
0,
b0 +
b0 *
0)
bx (
b0 '
bx &
bx %
0$
x#
bx "
0!
$end
#5
1!
#10
0!
#15
1!
#20
0!
b0 %
b0 (
b1001000110100 "
b1001000110100 &
0#
1$
#25
b1001000110100 *
1!
#30
0!
b1 %
b1 (
1#
#35
b111 '
b111 +
1)
1,
1!
#40
0!
b10 %
b10 (
#45
b110 '
b110 +
1!
#50
0!
b0 %
b0 (
b10001101000101 "
b10001101000101 &
#55
b10001101000101 *
b0 '
b0 +
0)
0,
1!
#60
0!
b1 %
b1 (
0#
#65
1)
1,
b1001 '
b1001 +
1!
#70
0!
#75
1!
#80
0!
#85
1!
#90
0!
1#
#95
1!
#100
0!
#105
1!
#110
0!
#115
1!
#120
0!
0#
#125
1!
#130
0!
#135
1!
#140
0!
1#
#145
1!
#150
0!
0#
