Others/FUNC.v
module test_FUNC;

    parameter PERIOD = 10;
    reg                       CLK = 1;
    reg                       CDN = 0;
    wire [4:0] Q;


    initial begin
        forever #(PERIOD / 2) CLK = ~CLK;
    end

    initial begin
        CDN = 1;
        #(PERIOD) CDN = 0;
        #(PERIOD) CDN = 1;
        // #(PERIOD * 200);
        // $finish;
    end

    FUNC u_FUNC(
    	.CLK (CLK ),
        .CDN (CDN ),
        .Q   (Q   )
    );

    initial begin
        $dumpfile("test_FUNC_wave.vcd");  //生成的vcd文件名称
        $dumpvars(0, test_FUNC);  //tb模块名称
        #20000 $finish;
    end
endmodule

module FUNC (CLK,CDN,Q);
    input CLK;
    input CDN;
    output [4:0] Q; 

    reg [4:0] Q_tmp;

    always @(posedge CLK or negedge CDN) begin
        if(!CDN)
            Q_tmp[0] <= 0;
        else begin
            Q_tmp[0] <= ~Q_tmp[0];
        end
    end

    always @(posedge CLK or negedge CDN) begin
        if(!CDN)
            Q_tmp[1] <= 0;
        else begin
            Q_tmp[1] <= Q_tmp[0] ^ Q_tmp[1];
        end
    end

    always @(posedge CLK or negedge CDN) begin
        if(!CDN)
            Q_tmp[2] <= 0;
        else begin
            Q_tmp[2] <= Q_tmp[2] ? (~(Q_tmp[0] & Q_tmp[1])) : (Q_tmp[0] & Q_tmp[1]);
        end
    end

    always @(posedge CLK or negedge CDN) begin
        if(!CDN)
            Q_tmp[3] <= 0;
        else begin
            Q_tmp[3] <= (Q_tmp[0] & Q_tmp[1] & Q_tmp[2]) ^ Q_tmp[3];
        end
    end

    always @(posedge CLK or negedge CDN) begin
        if(!CDN)
            Q_tmp[4] <= 0;
        else begin
            Q_tmp[4] <= Q_tmp[4] ^ (Q_tmp[0] & Q_tmp[1] & Q_tmp[2] & Q_tmp[3]);
        end
    end
    
    assign Q = Q_tmp;
endmodule //FUNC

Others/test_FUNC_wave.vcd
$date
	Sun May 07 15:17:14 2023
$end
$version
	Icarus Verilog
$end
$timescale
	1s
$end
$scope module test_FUNC $end
$var wire 5 ! Q [4:0] $end
$var reg 1 " CDN $end
$var reg 1 # CLK $end
$scope module u_FUNC $end
$var wire 1 " CDN $end
$var wire 1 # CLK $end
$var wire 5 $ Q [4:0] $end
$var reg 5 % Q_tmp [4:0] $end
$upscope $end
$upscope $end
$enddefinitions $end
#0
$dumpvars
bx %
bx $
1#
1"
bx !
$end
#5
0#
#10
b0 !
b0 $
b0 %
1#
0"
#15
0#
#20
b1 !
b1 $
b1 %
1#
1"
#25
0#
#30
b10 !
b10 $
b10 %
1#
#35
0#
#40
b11 !
b11 $
b11 %
1#
#45
0#
#50
b100 !
b100 $
b100 %
1#
#55
0#
#60
b101 !
b101 $
b101 %
1#
#65
0#
#70
b110 !
b110 $
b110 %
1#
#75
0#
#80
b111 !
b111 $
b111 %
1#
#85
0#
#90
b1000 !
b1000 $
b1000 %
1#
#95
0#
#100
b1001 !
b1001 $
b1001 %
1#
#105
0#
#110
b1010 !
b1010 $
b1010 %
1#
#115
0#
#120
b1011 !
b1011 $
b1011 %
1#
#125
0#
#130
b1100 !
b1100 $
b1100 %
1#
#135
0#
#140
b1101 !
b1101 $
b1101 %
1#
#145
0#
#150
b1110 !
b1110 $
b1110 %
1#
#155
0#
#160
b1111 !
b1111 $
b1111 %
1#
#165
0#
#170
b10000 !
b10000 $
b10000 %
1#
#175
0#
#180
b10001 !
b10001 $
b10001 %
1#
#185
0#
#190
b10010 !
b10010 $
b10010 %
1#
#195
0#
#200
b10011 !
b10011 $
b10011 %
1#
#205
0#
#210
b10100 !
b10100 $
b10100 %
1#
#215
0#
#220
b10101 !
b10101 $
b10101 %
1#
#225
0#
#230
b10110 !
b10110 $
b10110 %
1#
#235
0#
#240
b10111 !
b10111 $
b10111 %
1#
#245
0#
#250
b11000 !
b11000 $
b11000 %
1#
#255
0#
#260
b11001 !
b11001 $
b11001 %
1#
#265
0#
#270
b11010 !
b11010 $
b11010 %
1#
#275
0#
#280
b11011 !
b11011 $
b11011 %
1#
#285
0#
#290
b11100 !
b11100 $
b11100 %
1#
#295
0#
#300
b11101 !
b11101 $
b11101 %
1#
#305
0#
#310
b11110 !
b11110 $
b11110 %
1#
#315
0#
#320
b11111 !
b11111 $
b11111 %
1#
#325
0#
#330
b0 !
b0 $
b0 %
1#
#335
0#
#340
b1 !
b1 $
b1 %
1#
#345
0#
#350
b10 !
b10 $
b10 %
1#
#355
0#
#360
b11 !
b11 $
b11 %
1#
#365
0#
#370
b100 !
b100 $
b100 %
1#
#375
0#
#380
b101 !
b101 $
b101 %
1#
#385
0#
#390
b110 !
b110 $
b110 %
1#
#395
0#
#400
b111 !
b111 $
b111 %
1#
#405
0#
#410
b1000 !
b1000 $
b1000 %
1#
#415
0#
#420
b1001 !
b1001 $
b1001 %
1#
#425
0#
#430
b1010 !
b1010 $
b1010 %
1#
#435
0#
#440
b1011 !
b1011 $
b1011 %
1#
#445
0#
#450
b1100 !
b1100 $
b1100 %
1#
#455
0#
#460
b1101 !
b1101 $
b1101 %
1#
#465
0#
#470
b1110 !
b1110 $
b1110 %
1#
#475
0#
#480
b1111 !
b1111 $
b1111 %
1#
#485
0#
#490
b10000 !
b10000 $
b10000 %
1#
#495
0#
#500
b10001 !
b10001 $
b10001 %
1#
#505
0#
#510
b10010 !
b10010 $
b10010 %
1#
#515
0#
#520
b10011 !
b10011 $
b10011 %
1#
#525
0#
#530
b10100 !
b10100 $
b10100 %
1#
#535
0#
#540
b10101 !
b10101 $
b10101 %
1#
#545
0#
#550
b10110 !
b10110 $
b10110 %
1#
#555
0#
#560
b10111 !
b10111 $
b10111 %
1#
#565
0#
#570
b11000 !
b11000 $
b11000 %
1#
#575
0#
#580
b11001 !
b11001 $
b11001 %
1#
#585
0#
#590
b11010 !
b11010 $
b11010 %
1#
#595
0#
#600
b11011 !
b11011 $
b11011 %
1#
#605
0#
#610
b11100 !
b11100 $
b11100 %
1#
#615
0#
#620
b11101 !
b11101 $
b11101 %
1#
#625
0#
#630
b11110 !
b11110 $
b11110 %
1#
#635
0#
#640
b11111 !
b11111 $
b11111 %
1#
#645
0#
#650
b0 !
b0 $
b0 %
1#
#655
0#
#660
b1 !
b1 $
b1 %
1#
#665
0#
#670
b10 !
b10 $
b10 %
1#
#675
0#
#680
b11 !
b11 $
b11 %
1#
#685
0#
#690
b100 !
b100 $
b100 %
1#
#695
0#
#700
b101 !
b101 $
b101 %
1#
#705
0#
#710
b110 !
b110 $
b110 %
1#
#715
0#
#720
b111 !
b111 $
b111 %
1#
#725
0#
#730
b1000 !
b1000 $
b1000 %
1#
#735
0#
#740
b1001 !
b1001 $
b1001 %
1#
#745
0#
#750
b1010 !
b1010 $
b1010 %
1#
#755
0#
#760
b1011 !
b1011 $
b1011 %
1#
#765
0#
#770
b1100 !
b1100 $
b1100 %
1#
#775
0#
#780
b1101 !
b1101 $
b1101 %
1#
#785
0#
#790
b1110 !
b1110 $
b1110 %
1#
#795
0#
#800
b1111 !
b1111 $
b1111 %
1#
#805
0#
#810
b10000 !
b10000 $
b10000 %
1#
#815
0#
#820
b10001 !
b10001 $
b10001 %
1#
#825
0#
#830
b10010 !
b10010 $
b10010 %
1#
#835
0#
#840
b10011 !
b10011 $
b10011 %
1#
#845
0#
#850
b10100 !
b10100 $
b10100 %
1#
#855
0#
#860
b10101 !
b10101 $
b10101 %
1#
#865
0#
#870
b10110 !
b10110 $
b10110 %
1#
#875
0#
#880
b10111 !
b10111 $
b10111 %
1#
#885
0#
#890
b11000 !
b11000 $
b11000 %
1#
#895
0#
#900
b11001 !
b11001 $
b11001 %
1#
#905
0#
#910
b11010 !
b11010 $
b11010 %
1#
#915
0#
#920
b11011 !
b11011 $
b11011 %
1#
#925
0#
#930
b11100 !
b11100 $
b11100 %
1#
#935
0#
#940
b11101 !
b11101 $
b11101 %
1#
#945
0#
#950
b11110 !
b11110 $
b11110 %
1#
#955
0#
#960
b11111 !
b11111 $
b11111 %
1#
#965
0#
#970
b0 !
b0 $
b0 %
1#
#975
0#
#980
b1 !
b1 $
b1 %
1#
#985
0#
#990
b10 !
b10 $
b10 %
1#
#995
0#
#1000
b11 !
b11 $
b11 %
1#
#1005
0#
#1010
b100 !
b100 $
b100 %
1#
#1015
0#
#1020
b101 !
b101 $
b101 %
1#
#1025
0#
#1030
b110 !
b110 $
b110 %
1#
#1035
0#
#1040
b111 !
b111 $
b111 %
1#
#1045
0#
#1050
b1000 !
b1000 $
b1000 %
1#
#1055
0#
#1060
b1001 !
b1001 $
b1001 %
1#
#1065
0#
#1070
b1010 !
b1010 $
b1010 %
1#
#1075
0#
#1080
b1011 !
b1011 $
b1011 %
1#
#1085
0#
#1090
b1100 !
b1100 $
b1100 %
1#
#1095
0#
#1100
b1101 !
b1101 $
b1101 %
1#
#1105
0#
#1110
b1110 !
b1110 $
b1110 %
1#
#1115
0#
#1120
b1111 !
b1111 $
b1111 %
1#
#1125
0#
#1130
b10000 !
b10000 $
b10000 %
1#
#1135
0#
#1140
b10001 !
b10001 $
b10001 %
1#
#1145
0#
#1150
b10010 !
b10010 $
b10010 %
1#
#1155
0#
#1160
b10011 !
b10011 $
b10011 %
1#
#1165
0#
#1170
b10100 !
b10100 $
b10100 %
1#
#1175
0#
#1180
b10101 !
b10101 $
b10101 %
1#
#1185
0#
#1190
b10110 !
b10110 $
b10110 %
1#
#1195
0#
#1200
b10111 !
b10111 $
b10111 %
1#
#1205
0#
#1210
b11000 !
b11000 $
b11000 %
1#
#1215
0#
#1220
b11001 !
b11001 $
b11001 %
1#
#1225
0#
#1230
b11010 !
b11010 $
b11010 %
1#
#1235
0#
#1240
b11011 !
b11011 $
b11011 %
1#
#1245
0#
#1250
b11100 !
b11100 $
b11100 %
1#
#1255
0#
#1260
b11101 !
b11101 $
b11101 %
1#
#1265
0#
#1270
b11110 !
b11110 $
b11110 %
1#
#1275
0#
#1280
b11111 !
b11111 $
b11111 %
1#
#1285
0#
#1290
b0 !
b0 $
b0 %
1#
#1295
0#
#1300
b1 !
b1 $
b1 %
1#
#1305
0#
#1310
b10 !
b10 $
b10 %
1#
#1315
0#
#1320
b11 !
b11 $
b11 %
1#
#1325
0#
#1330
b100 !
b100 $
b100 %
1#
#1335
0#
#1340
b101 !
b101 $
b101 %
1#
#1345
0#
#1350
b110 !
b110 $
b110 %
1#
#1355
0#
#1360
b111 !
b111 $
b111 %
1#
#1365
0#
#1370
b1000 !
b1000 $
b1000 %
1#
#1375
0#
#1380
b1001 !
b1001 $
b1001 %
1#
#1385
0#
#1390
b1010 !
b1010 $
b1010 %
1#
#1395
0#
#1400
b1011 !
b1011 $
b1011 %
1#
#1405
0#
#1410
b1100 !
b1100 $
b1100 %
1#
#1415
0#
#1420
b1101 !
b1101 $
b1101 %
1#
#1425
0#
#1430
b1110 !
b1110 $
b1110 %
1#
#1435
0#
#1440
b1111 !
b1111 $
b1111 %
1#
#1445
0#
#1450
b10000 !
b10000 $
b10000 %
1#
#1455
0#
#1460
b10001 !
b10001 $
b10001 %
1#
#1465
0#
#1470
b10010 !
b10010 $
b10010 %
1#
#1475
0#
#1480
b10011 !
b10011 $
b10011 %
1#
#1485
0#
#1490
b10100 !
b10100 $
b10100 %
1#
#1495
0#
#1500
b10101 !
b10101 $
b10101 %
1#
#1505
0#
#1510
b10110 !
b10110 $
b10110 %
1#
#1515
0#
#1520
b10111 !
b10111 $
b10111 %
1#
#1525
0#
#1530
b11000 !
b11000 $
b11000 %
1#
#1535
0#
#1540
b11001 !
b11001 $
b11001 %
1#
#1545
0#
#1550
b11010 !
b11010 $
b11010 %
1#
#1555
0#
#1560
b11011 !
b11011 $
b11011 %
1#
#1565
0#
#1570
b11100 !
b11100 $
b11100 %
1#
#1575
0#
#1580
b11101 !
b11101 $
b11101 %
1#
#1585
0#
#1590
b11110 !
b11110 $
b11110 %
1#
#1595
0#
#1600
b11111 !
b11111 $
b11111 %
1#
#1605
0#
#1610
b0 !
b0 $
b0 %
1#
#1615
0#
#1620
b1 !
b1 $
b1 %
1#
#1625
0#
#1630
b10 !
b10 $
b10 %
1#
#1635
0#
#1640
b11 !
b11 $
b11 %
1#
#1645
0#
#1650
b100 !
b100 $
b100 %
1#
#1655
0#
#1660
b101 !
b101 $
b101 %
1#
#1665
0#
#1670
b110 !
b110 $
b110 %
1#
#1675
0#
#1680
b111 !
b111 $
b111 %
1#
#1685
0#
#1690
b1000 !
b1000 $
b1000 %
1#
#1695
0#
#1700
b1001 !
b1001 $
b1001 %
1#
#1705
0#
#1710
b1010 !
b1010 $
b1010 %
1#
#1715
0#
#1720
b1011 !
b1011 $
b1011 %
1#
#1725
0#
#1730
b1100 !
b1100 $
b1100 %
1#
#1735
0#
#1740
b1101 !
b1101 $
b1101 %
1#
#1745
0#
#1750
b1110 !
b1110 $
b1110 %
1#
#1755
0#
#1760
b1111 !
b1111 $
b1111 %
1#
#1765
0#
#1770
b10000 !
b10000 $
b10000 %
1#
#1775
0#
#1780
b10001 !
b10001 $
b10001 %
1#
#1785
0#
#1790
b10010 !
b10010 $
b10010 %
1#
#1795
0#
#1800
b10011 !
b10011 $
b10011 %
1#
#1805
0#
#1810
b10100 !
b10100 $
b10100 %
1#
#1815
0#
#1820
b10101 !
b10101 $
b10101 %
1#
#1825
0#
#1830
b10110 !
b10110 $
b10110 %
1#
#1835
0#
#1840
b10111 !
b10111 $
b10111 %
1#
#1845
0#
#1850
b11000 !
b11000 $
b11000 %
1#
#1855
0#
#1860
b11001 !
b11001 $
b11001 %
1#
#1865
0#
#1870
b11010 !
b11010 $
b11010 %
1#
#1875
0#
#1880
b11011 !
b11011 $
b11011 %
1#
#1885
0#
#1890
b11100 !
b11100 $
b11100 %
1#
#1895
0#
#1900
b11101 !
b11101 $
b11101 %
1#
#1905
0#
#1910
b11110 !
b11110 $
b11110 %
1#
#1915
0#
#1920
b11111 !
b11111 $
b11111 %
1#
#1925
0#
#1930
b0 !
b0 $
b0 %
1#
#1935
0#
#1940
b1 !
b1 $
b1 %
1#
#1945
0#
#1950
b10 !
b10 $
b10 %
1#
#1955
0#
#1960
b11 !
b11 $
b11 %
1#
#1965
0#
#1970
b100 !
b100 $
b100 %
1#
#1975
0#
#1980
b101 !
b101 $
b101 %
1#
#1985
0#
#1990
b110 !
b110 $
b110 %
1#
#1995
0#
#2000
b111 !
b111 $
b111 %
1#
#2005
0#
#2010
b1000 !
b1000 $
b1000 %
1#
#2015
0#
#2020
b1001 !
b1001 $
b1001 %
1#
#2025
0#
#2030
b1010 !
b1010 $
b1010 %
1#
#2035
0#
#2040
b1011 !
b1011 $
b1011 %
1#
#2045
0#
#2050
b1100 !
b1100 $
b1100 %
1#
#2055
0#
#2060
b1101 !
b1101 $
b1101 %
1#
#2065
0#
#2070
b1110 !
b1110 $
b1110 %
1#
#2075
0#
#2080
b1111 !
b1111 $
b1111 %
1#
#2085
0#
#2090
b10000 !
b10000 $
b10000 %
1#
#2095
0#
#2100
b10001 !
b10001 $
b10001 %
1#
#2105
0#
#2110
b10010 !
b10010 $
b10010 %
1#
#2115
0#
#2120
b10011 !
b10011 $
b10011 %
1#
#2125
0#
#2130
b10100 !
b10100 $
b10100 %
1#
#2135
0#
#2140
b10101 !
b10101 $
b10101 %
1#
#2145
0#
#2150
b10110 !
b10110 $
b10110 %
1#
#2155
0#
#2160
b10111 !
b10111 $
b10111 %
1#
#2165
0#
#2170
b11000 !
b11000 $
b11000 %
1#
#2175
0#
#2180
b11001 !
b11001 $
b11001 %
1#
#2185
0#
#2190
b11010 !
b11010 $
b11010 %
1#
#2195
0#
#2200
b11011 !
b11011 $
b11011 %
1#
#2205
0#
#2210
b11100 !
b11100 $
b11100 %
1#
#2215
0#
#2220
b11101 !
b11101 $
b11101 %
1#
#2225
0#
#2230
b11110 !
b11110 $
b11110 %
1#
#2235
0#
#2240
b11111 !
b11111 $
b11111 %
1#
#2245
0#
#2250
b0 !
b0 $
b0 %
1#
#2255
0#
#2260
b1 !
b1 $
b1 %
1#
#2265
0#
#2270
b10 !
b10 $
b10 %
1#
#2275
0#
#2280
b11 !
b11 $
b11 %
1#
#2285
0#
#2290
b100 !
b100 $
b100 %
1#
#2295
0#
#2300
b101 !
b101 $
b101 %
1#
#2305
0#
#2310
b110 !
b110 $
b110 %
1#
#2315
0#
#2320
b111 !
b111 $
b111 %
1#
#2325
0#
#2330
b1000 !
b1000 $
b1000 %
1#
#2335
0#
#2340
b1001 !
b1001 $
b1001 %
1#
#2345
0#
#2350
b1010 !
b1010 $
b1010 %
1#
#2355
0#
#2360
b1011 !
b1011 $
b1011 %
1#
#2365
0#
#2370
b1100 !
b1100 $
b1100 %
1#
#2375
0#
#2380
b1101 !
b1101 $
b1101 %
1#
#2385
0#
#2390
b1110 !
b1110 $
b1110 %
1#
#2395
0#
#2400
b1111 !
b1111 $
b1111 %
1#
#2405
0#
#2410
b10000 !
b10000 $
b10000 %
1#
#2415
0#
#2420
b10001 !
b10001 $
b10001 %
1#
#2425
0#
#2430
b10010 !
b10010 $
b10010 %
1#
#2435
0#
#2440
b10011 !
b10011 $
b10011 %
1#
#2445
0#
#2450
b10100 !
b10100 $
b10100 %
1#
#2455
0#
#2460
b10101 !
b10101 $
b10101 %
1#
#2465
0#
#2470
b10110 !
b10110 $
b10110 %
1#
#2475
0#
#2480
b10111 !
b10111 $
b10111 %
1#
#2485
0#
#2490
b11000 !
b11000 $
b11000 %
1#
#2495
0#
#2500
b11001 !
b11001 $
b11001 %
1#
#2505
0#
#2510
b11010 !
b11010 $
b11010 %
1#
#2515
0#
#2520
b11011 !
b11011 $
b11011 %
1#
#2525
0#
#2530
b11100 !
b11100 $
b11100 %
1#
#2535
0#
#2540
b11101 !
b11101 $
b11101 %
1#
#2545
0#
#2550
b11110 !
b11110 $
b11110 %
1#
#2555
0#
#2560
b11111 !
b11111 $
b11111 %
1#
#2565
0#
#2570
b0 !
b0 $
b0 %
1#
#2575
0#
#2580
b1 !
b1 $
b1 %
1#
#2585
0#
#2590
b10 !
b10 $
b10 %
1#
#2595
0#
#2600
b11 !
b11 $
b11 %
1#
#2605
0#
#2610
b100 !
b100 $
b100 %
1#
#2615
0#
#2620
b101 !
b101 $
b101 %
1#
#2625
0#
#2630
b110 !
b110 $
b110 %
1#
#2635
0#
#2640
b111 !
b111 $
b111 %
1#
#2645
0#
#2650
b1000 !
b1000 $
b1000 %
1#
#2655
0#
#2660
b1001 !
b1001 $
b1001 %
1#
#2665
0#
#2670
b1010 !
b1010 $
b1010 %
1#
#2675
0#
#2680
b1011 !
b1011 $
b1011 %
1#
#2685
0#
#2690
b1100 !
b1100 $
b1100 %
1#
#2695
0#
#2700
b1101 !
b1101 $
b1101 %
1#
#2705
0#
#2710
b1110 !
b1110 $
b1110 %
1#
#2715
0#
#2720
b1111 !
b1111 $
b1111 %
1#
#2725
0#
#2730
b10000 !
b10000 $
b10000 %
1#
#2735
0#
#2740
b10001 !
b10001 $
b10001 %
1#
#2745
0#
#2750
b10010 !
b10010 $
b10010 %
1#
#2755
0#
#2760
b10011 !
b10011 $
b10011 %
1#
#2765
0#
#2770
b10100 !
b10100 $
b10100 %
1#
#2775
0#
#2780
b10101 !
b10101 $
b10101 %
1#
#2785
0#
#2790
b10110 !
b10110 $
b10110 %
1#
#2795
0#
#2800
b10111 !
b10111 $
b10111 %
1#
#2805
0#
#2810
b11000 !
b11000 $
b11000 %
1#
#2815
0#
#2820
b11001 !
b11001 $
b11001 %
1#
#2825
0#
#2830
b11010 !
b11010 $
b11010 %
1#
#2835
0#
#2840
b11011 !
b11011 $
b11011 %
1#
#2845
0#
#2850
b11100 !
b11100 $
b11100 %
1#
#2855
0#
#2860
b11101 !
b11101 $
b11101 %
1#
#2865
0#
#2870
b11110 !
b11110 $
b11110 %
1#
#2875
0#
#2880
b11111 !
b11111 $
b11111 %
1#
#2885
0#
#2890
b0 !
b0 $
b0 %
1#
#2895
0#
#2900
b1 !
b1 $
b1 %
1#
#2905
0#
#2910
b10 !
b10 $
b10 %
1#
#2915
0#
#2920
b11 !
b11 $
b11 %
1#
#2925
0#
#2930
b100 !
b100 $
b100 %
1#
#2935
0#
#2940
b101 !
b101 $
b101 %
1#
#2945
0#
#2950
b110 !
b110 $
b110 %
1#
#2955
0#
#2960
b111 !
b111 $
b111 %
1#
#2965
0#
#2970
b1000 !
b1000 $
b1000 %
1#
#2975
0#
#2980
b1001 !
b1001 $
b1001 %
1#
#2985
0#
#2990
b1010 !
b1010 $
b1010 %
1#
#2995
0#
#3000
b1011 !
b1011 $
b1011 %
1#
#3005
0#
#3010
b1100 !
b1100 $
b1100 %
1#
#3015
0#
#3020
b1101 !
b1101 $
b1101 %
1#
#3025
0#
#3030
b1110 !
b1110 $
b1110 %
1#
#3035
0#
#3040
b1111 !
b1111 $
b1111 %
1#
#3045
0#
#3050
b10000 !
b10000 $
b10000 %
1#
#3055
0#
#3060
b10001 !
b10001 $
b10001 %
1#
#3065
0#
#3070
b10010 !
b10010 $
b10010 %
1#
#3075
0#
#3080
b10011 !
b10011 $
b10011 %
1#
#3085
0#
#3090
b10100 !
b10100 $
b10100 %
1#
#3095
0#
#3100
b10101 !
b10101 $
b10101 %
1#
#3105
0#
#3110
b10110 !
b10110 $
b10110 %
1#
#3115
0#
#3120
b10111 !
b10111 $
b10111 %
1#
#3125
0#
#3130
b11000 !
b11000 $
b11000 %
1#
#3135
0#
#3140
b11001 !
b11001 $
b11001 %
1#
#3145
0#
#3150
b11010 !
b11010 $
b11010 %
1#
#3155
0#
#3160
b11011 !
b11011 $
b11011 %
1#
#3165
0#
#3170
b11100 !
b11100 $
b11100 %
1#
#3175
0#
#3180
b11101 !
b11101 $
b11101 %
1#
#3185
0#
#3190
b11110 !
b11110 $
b11110 %
1#
#3195
0#
#3200
b11111 !
b11111 $
b11111 %
1#
#3205
0#
#3210
b0 !
b0 $
b0 %
1#
#3215
0#
#3220
b1 !
b1 $
b1 %
1#
#3225
0#
#3230
b10 !
b10 $
b10 %
1#
#3235
0#
#3240
b11 !
b11 $
b11 %
1#
#3245
0#
#3250
b100 !
b100 $
b100 %
1#
#3255
0#
#3260
b101 !
b101 $
b101 %
1#
#3265
0#
#3270
b110 !
b110 $
b110 %
1#
#3275
0#
#3280
b111 !
b111 $
b111 %
1#
#3285
0#
#3290
b1000 !
b1000 $
b1000 %
1#
#3295
0#
#3300
b1001 !
b1001 $
b1001 %
1#
#3305
0#
#3310
b1010 !
b1010 $
b1010 %
1#
#3315
0#
#3320
b1011 !
b1011 $
b1011 %
1#
#3325
0#
#3330
b1100 !
b1100 $
b1100 %
1#
#3335
0#
#3340
b1101 !
b1101 $
b1101 %
1#
#3345
0#
#3350
b1110 !
b1110 $
b1110 %
1#
#3355
0#
#3360
b1111 !
b1111 $
b1111 %
1#
#3365
0#
#3370
b10000 !
b10000 $
b10000 %
1#
#3375
0#
#3380
b10001 !
b10001 $
b10001 %
1#
#3385
0#
#3390
b10010 !
b10010 $
b10010 %
1#
#3395
0#
#3400
b10011 !
b10011 $
b10011 %
1#
#3405
0#
#3410
b10100 !
b10100 $
b10100 %
1#
#3415
0#
#3420
b10101 !
b10101 $
b10101 %
1#
#3425
0#
#3430
b10110 !
b10110 $
b10110 %
1#
#3435
0#
#3440
b10111 !
b10111 $
b10111 %
1#
#3445
0#
#3450
b11000 !
b11000 $
b11000 %
1#
#3455
0#
#3460
b11001 !
b11001 $
b11001 %
1#
#3465
0#
#3470
b11010 !
b11010 $
b11010 %
1#
#3475
0#
#3480
b11011 !
b11011 $
b11011 %
1#
#3485
0#
#3490
b11100 !
b11100 $
b11100 %
1#
#3495
0#
#3500
b11101 !
b11101 $
b11101 %
1#
#3505
0#
#3510
b11110 !
b11110 $
b11110 %
1#
#3515
0#
#3520
b11111 !
b11111 $
b11111 %
1#
#3525
0#
#3530
b0 !
b0 $
b0 %
1#
#3535
0#
#3540
b1 !
b1 $
b1 %
1#
#3545
0#
#3550
b10 !
b10 $
b10 %
1#
#3555
0#
#3560
b11 !
b11 $
b11 %
1#
#3565
0#
#3570
b100 !
b100 $
b100 %
1#
#3575
0#
#3580
b101 !
b101 $
b101 %
1#
#3585
0#
#3590
b110 !
b110 $
b110 %
1#
#3595
0#
#3600
b111 !
b111 $
b111 %
1#
#3605
0#
#3610
b1000 !
b1000 $
b1000 %
1#
#3615
0#
#3620
b1001 !
b1001 $
b1001 %
1#
#3625
0#
#3630
b1010 !
b1010 $
b1010 %
1#
#3635
0#
#3640
b1011 !
b1011 $
b1011 %
1#
#3645
0#
#3650
b1100 !
b1100 $
b1100 %
1#
#3655
0#
#3660
b1101 !
b1101 $
b1101 %
1#
#3665
0#
#3670
b1110 !
b1110 $
b1110 %
1#
#3675
0#
#3680
b1111 !
b1111 $
b1111 %
1#
#3685
0#
#3690
b10000 !
b10000 $
b10000 %
1#
#3695
0#
#3700
b10001 !
b10001 $
b10001 %
1#
#3705
0#
#3710
b10010 !
b10010 $
b10010 %
1#
#3715
0#
#3720
b10011 !
b10011 $
b10011 %
1#
#3725
0#
#3730
b10100 !
b10100 $
b10100 %
1#
#3735
0#
#3740
b10101 !
b10101 $
b10101 %
1#
#3745
0#
#3750
b10110 !
b10110 $
b10110 %
1#
#3755
0#
#3760
b10111 !
b10111 $
b10111 %
1#
#3765
0#
#3770
b11000 !
b11000 $
b11000 %
1#
#3775
0#
#3780
b11001 !
b11001 $
b11001 %
1#
#3785
0#
#3790
b11010 !
b11010 $
b11010 %
1#
#3795
0#
#3800
b11011 !
b11011 $
b11011 %
1#
#3805
0#
#3810
b11100 !
b11100 $
b11100 %
1#
#3815
0#
#3820
b11101 !
b11101 $
b11101 %
1#
#3825
0#
#3830
b11110 !
b11110 $
b11110 %
1#
#3835
0#
#3840
b11111 !
b11111 $
b11111 %
1#
#3845
0#
#3850
b0 !
b0 $
b0 %
1#
#3855
0#
#3860
b1 !
b1 $
b1 %
1#
#3865
0#
#3870
b10 !
b10 $
b10 %
1#
#3875
0#
#3880
b11 !
b11 $
b11 %
1#
#3885
0#
#3890
b100 !
b100 $
b100 %
1#
#3895
0#
#3900
b101 !
b101 $
b101 %
1#
#3905
0#
#3910
b110 !
b110 $
b110 %
1#
#3915
0#
#3920
b111 !
b111 $
b111 %
1#
#3925
0#
#3930
b1000 !
b1000 $
b1000 %
1#
#3935
0#
#3940
b1001 !
b1001 $
b1001 %
1#
#3945
0#
#3950
b1010 !
b1010 $
b1010 %
1#
#3955
0#
#3960
b1011 !
b1011 $
b1011 %
1#
#3965
0#
#3970
b1100 !
b1100 $
b1100 %
1#
#3975
0#
#3980
b1101 !
b1101 $
b1101 %
1#
#3985
0#
#3990
b1110 !
b1110 $
b1110 %
1#
#3995
0#
#4000
b1111 !
b1111 $
b1111 %
1#
#4005
0#
#4010
b10000 !
b10000 $
b10000 %
1#
#4015
0#
#4020
b10001 !
b10001 $
b10001 %
1#
#4025
0#
#4030
b10010 !
b10010 $
b10010 %
1#
#4035
0#
#4040
b10011 !
b10011 $
b10011 %
1#
#4045
0#
#4050
b10100 !
b10100 $
b10100 %
1#
#4055
0#
#4060
b10101 !
b10101 $
b10101 %
1#
#4065
0#
#4070
b10110 !
b10110 $
b10110 %
1#
#4075
0#
#4080
b10111 !
b10111 $
b10111 %
1#
#4085
0#
#4090
b11000 !
b11000 $
b11000 %
1#
#4095
0#
#4100
b11001 !
b11001 $
b11001 %
1#
#4105
0#
#4110
b11010 !
b11010 $
b11010 %
1#
#4115
0#
#4120
b11011 !
b11011 $
b11011 %
1#
#4125
0#
#4130
b11100 !
b11100 $
b11100 %
1#
#4135
0#
#4140
b11101 !
b11101 $
b11101 %
1#
#4145
0#
#4150
b11110 !
b11110 $
b11110 %
1#
#4155
0#
#4160
b11111 !
b11111 $
b11111 %
1#
#4165
0#
#4170
b0 !
b0 $
b0 %
1#
#4175
0#
#4180
b1 !
b1 $
b1 %
1#
#4185
0#
#4190
b10 !
b10 $
b10 %
1#
#4195
0#
#4200
b11 !
b11 $
b11 %
1#
#4205
0#
#4210
b100 !
b100 $
b100 %
1#
#4215
0#
#4220
b101 !
b101 $
b101 %
1#
#4225
0#
#4230
b110 !
b110 $
b110 %
1#
#4235
0#
#4240
b111 !
b111 $
b111 %
1#
#4245
0#
#4250
b1000 !
b1000 $
b1000 %
1#
#4255
0#
#4260
b1001 !
b1001 $
b1001 %
1#
#4265
0#
#4270
b1010 !
b1010 $
b1010 %
1#
#4275
0#
#4280
b1011 !
b1011 $
b1011 %
1#
#4285
0#
#4290
b1100 !
b1100 $
b1100 %
1#
#4295
0#
#4300
b1101 !
b1101 $
b1101 %
1#
#4305
0#
#4310
b1110 !
b1110 $
b1110 %
1#
#4315
0#
#4320
b1111 !
b1111 $
b1111 %
1#
#4325
0#
#4330
b10000 !
b10000 $
b10000 %
1#
#4335
0#
#4340
b10001 !
b10001 $
b10001 %
1#
#4345
0#
#4350
b10010 !
b10010 $
b10010 %
1#
#4355
0#
#4360
b10011 !
b10011 $
b10011 %
1#
#4365
0#
#4370
b10100 !
b10100 $
b10100 %
1#
#4375
0#
#4380
b10101 !
b10101 $
b10101 %
1#
#4385
0#
#4390
b10110 !
b10110 $
b10110 %
1#
#4395
0#
#4400
b10111 !
b10111 $
b10111 %
1#
#4405
0#
#4410
b11000 !
b11000 $
b11000 %
1#
#4415
0#
#4420
b11001 !
b11001 $
b11001 %
1#
#4425
0#
#4430
b11010 !
b11010 $
b11010 %
1#
#4435
0#
#4440
b11011 !
b11011 $
b11011 %
1#
#4445
0#
#4450
b11100 !
b11100 $
b11100 %
1#
#4455
0#
#4460
b11101 !
b11101 $
b11101 %
1#
#4465
0#
#4470
b11110 !
b11110 $
b11110 %
1#
#4475
0#
