Others/test.v
`timescale 1ns / 1ps
module test_module;
    reg       clk = 1;
    reg       rst = 1;
    reg       a;
    reg [1:0] b;
    parameter PERIOD = 10;

    initial begin
        forever #(PERIOD / 2) clk = ~clk;
    end

    initial begin
        #PERIOD rst = 0;
        #PERIOD rst = 1;
        #PERIOD a = 1;
        b = 2'b10;
    end
    Even_Freq_Div_N U_Even_Freq_Div_N (
        .clk_in (clk),
        .rst_n  (rst),
        .clk_out(clkout)

    );

    ////////////////////////////////////////////////////////////
    initial begin
        $dumpfile("wave.vcd");  //生成的vcd文件名称
        $dumpvars(0, test_module);  //tb模块名称
        #2000 $finish;
    end
    ////////////////////////////////////////////////////////////

endmodule

module Even_Freq_Div_N (
    input      clk_in,
    input      rst_n,
    output reg clk_out
);

    reg [3:0] cnt;
    parameter N = 7;

    always @(posedge clk_in or negedge rst_n) begin
        if (!rst_n) begin
            cnt <= 4'b0000;
        end else if (cnt == N-1) begin
            cnt <= 4'b0000;
        end else begin
            cnt <= cnt + 1'b1;
        end
    end

    always @(posedge clk_in or negedge rst_n) begin
        if (!rst_n) begin
            clk_out <= 0;
        end else if (cnt == ((N-1) / 2)) begin
            clk_out <= ~clk_out;
        end else if (cnt == 0) begin
            clk_out <= ~clk_out;
        end else begin
            clk_out <= clk_out;
        end
    end

endmodule

Others/wave.vcd
$date
	Sat Oct 07 12:18:17 2023
$end
$version
	Icarus Verilog
$end
$timescale
	1ps
$end
$scope module test_module $end
$var wire 1 ! clkout $end
$var reg 1 " a $end
$var reg 2 # b [1:0] $end
$var reg 1 $ clk $end
$var reg 1 % rst $end
$scope module U_Even_Freq_Div_N $end
$var wire 1 $ clk_in $end
$var wire 1 % rst_n $end
$var reg 1 ! clk_out $end
$var reg 4 & cnt [3:0] $end
$upscope $end
$upscope $end
$enddefinitions $end
#0
$dumpvars
bx &
1%
1$
bx #
x"
x!
$end
#5000
0$
#10000
0!
b0 &
1$
0%
#15000
0$
#20000
b1 &
1!
1$
1%
#25000
0$
#30000
b10 &
1$
b10 #
1"
#35000
0$
#40000
b11 &
1$
#45000
0$
#50000
0!
b100 &
1$
#55000
0$
#60000
b101 &
1$
#65000
0$
#70000
b110 &
1$
#75000
0$
#80000
b0 &
1$
#85000
0$
#90000
1!
b1 &
1$
#95000
0$
#100000
b10 &
1$
#105000
0$
#110000
b11 &
1$
#115000
0$
#120000
b100 &
0!
1$
#125000
0$
#130000
b101 &
1$
#135000
0$
#140000
b110 &
1$
#145000
0$
#150000
b0 &
1$
#155000
0$
#160000
b1 &
1!
1$
#165000
0$
#170000
b10 &
1$
#175000
0$
#180000
b11 &
1$
#185000
0$
#190000
0!
b100 &
1$
#195000
0$
#200000
b101 &
1$
#205000
0$
#210000
b110 &
1$
#215000
0$
#220000
b0 &
1$
#225000
0$
#230000
1!
b1 &
1$
#235000
0$
#240000
b10 &
1$
#245000
0$
#250000
b11 &
1$
#255000
0$
#260000
b100 &
0!
1$
#265000
0$
#270000
b101 &
1$
#275000
0$
#280000
b110 &
1$
#285000
0$
#290000
b0 &
1$
#295000
0$
#300000
b1 &
1!
1$
#305000
0$
#310000
b10 &
1$
#315000
0$
#320000
b11 &
1$
#325000
0$
#330000
0!
b100 &
1$
#335000
0$
#340000
b101 &
1$
#345000
0$
#350000
b110 &
1$
#355000
0$
#360000
b0 &
1$
#365000
0$
#370000
1!
b1 &
1$
#375000
0$
#380000
b10 &
1$
#385000
0$
#390000
b11 &
1$
#395000
0$
#400000
b100 &
0!
1$
#405000
0$
#410000
b101 &
1$
#415000
0$
#420000
b110 &
1$
#425000
0$
#430000
b0 &
1$
#435000
0$
#440000
b1 &
1!
1$
#445000
0$
#450000
b10 &
1$
#455000
0$
#460000
b11 &
1$
#465000
0$
#470000
0!
b100 &
1$
#475000
0$
#480000
b101 &
1$
#485000
0$
#490000
b110 &
1$
#495000
0$
#500000
b0 &
1$
#505000
0$
#510000
1!
b1 &
1$
#515000
0$
#520000
b10 &
1$
#525000
0$
#530000
b11 &
1$
#535000
0$
#540000
b100 &
0!
1$
#545000
0$
#550000
b101 &
1$
#555000
0$
#560000
b110 &
1$
#565000
0$
#570000
b0 &
1$
#575000
0$
#580000
b1 &
1!
1$
#585000
0$
#590000
b10 &
1$
#595000
0$
#600000
b11 &
1$
#605000
0$
#610000
0!
b100 &
1$
#615000
0$
#620000
b101 &
1$
#625000
0$
#630000
b110 &
1$
#635000
0$
#640000
b0 &
1$
#645000
0$
#650000
1!
b1 &
1$
#655000
0$
#660000
b10 &
1$
#665000
0$
#670000
b11 &
1$
#675000
0$
#680000
b100 &
0!
1$
#685000
0$
#690000
b101 &
1$
#695000
0$
#700000
b110 &
1$
#705000
0$
#710000
b0 &
1$
#715000
0$
#720000
b1 &
1!
1$
#725000
0$
#730000
b10 &
1$
#735000
0$
#740000
b11 &
1$
#745000
0$
#750000
0!
b100 &
1$
#755000
0$
#760000
b101 &
1$
#765000
0$
#770000
b110 &
1$
#775000
0$
#780000
b0 &
1$
#785000
0$
#790000
1!
b1 &
1$
#795000
0$
#800000
b10 &
1$
#805000
0$
#810000
b11 &
1$
#815000
0$
#820000
b100 &
0!
1$
#825000
0$
#830000
b101 &
1$
#835000
0$
#840000
b110 &
1$
#845000
0$
#850000
b0 &
1$
#855000
0$
#860000
b1 &
1!
1$
#865000
0$
#870000
b10 &
1$
#875000
0$
#880000
b11 &
1$
#885000
0$
#890000
0!
b100 &
1$
#895000
0$
#900000
b101 &
1$
#905000
0$
#910000
b110 &
1$
#915000
0$
#920000
b0 &
1$
#925000
0$
#930000
1!
b1 &
1$
#935000
0$
#940000
b10 &
1$
#945000
0$
#950000
b11 &
1$
#955000
0$
#960000
b100 &
0!
1$
#965000
0$
#970000
b101 &
1$
#975000
0$
#980000
b110 &
1$
#985000
0$
#990000
b0 &
1$
#995000
0$
#1000000
b1 &
1!
1$
#1005000
0$
#1010000
b10 &
1$
#1015000
0$
#1020000
b11 &
1$
#1025000
0$
#1030000
0!
b100 &
1$
#1035000
0$
#1040000
b101 &
1$
#1045000
0$
#1050000
b110 &
1$
#1055000
0$
#1060000
b0 &
1$
#1065000
0$
#1070000
1!
b1 &
1$
#1075000
0$
#1080000
b10 &
1$
#1085000
0$
#1090000
b11 &
1$
#1095000
0$
#1100000
b100 &
0!
1$
#1105000
0$
#1110000
b101 &
1$
#1115000
0$
#1120000
b110 &
1$
#1125000
0$
#1130000
b0 &
1$
#1135000
0$
#1140000
b1 &
1!
1$
#1145000
0$
#1150000
b10 &
1$
#1155000
0$
#1160000
b11 &
1$
#1165000
0$
#1170000
0!
b100 &
1$
#1175000
0$
#1180000
b101 &
1$
#1185000
0$
#1190000
b110 &
1$
#1195000
0$
#1200000
b0 &
1$
#1205000
0$
#1210000
1!
b1 &
1$
#1215000
0$
#1220000
b10 &
1$
#1225000
0$
#1230000
b11 &
1$
#1235000
0$
#1240000
b100 &
0!
1$
#1245000
0$
#1250000
b101 &
1$
#1255000
0$
#1260000
b110 &
1$
#1265000
0$
#1270000
b0 &
1$
#1275000
0$
#1280000
b1 &
1!
1$
#1285000
0$
#1290000
b10 &
1$
#1295000
0$
#1300000
b11 &
1$
#1305000
0$
#1310000
0!
b100 &
1$
#1315000
0$
#1320000
b101 &
1$
#1325000
0$
#1330000
b110 &
1$
#1335000
0$
#1340000
b0 &
1$
#1345000
0$
#1350000
1!
b1 &
1$
#1355000
0$
#1360000
b10 &
1$
#1365000
0$
#1370000
b11 &
1$
#1375000
0$
#1380000
b100 &
0!
1$
#1385000
0$
#1390000
b101 &
1$
#1395000
0$
#1400000
b110 &
1$
#1405000
0$
#1410000
b0 &
1$
#1415000
0$
#1420000
b1 &
1!
1$
#1425000
0$
#1430000
b10 &
1$
#1435000
0$
#1440000
b11 &
1$
#1445000
0$
#1450000
0!
b100 &
1$
#1455000
0$
#1460000
b101 &
1$
#1465000
0$
#1470000
b110 &
1$
#1475000
0$
#1480000
b0 &
1$
#1485000
0$
#1490000
1!
b1 &
1$
#1495000
0$
#1500000
b10 &
1$
#1505000
0$
#1510000
b11 &
1$
#1515000
0$
#1520000
b100 &
0!
1$
#1525000
0$
#1530000
b101 &
1$
#1535000
0$
#1540000
b110 &
1$
#1545000
0$
#1550000
b0 &
1$
#1555000
0$
#1560000
b1 &
1!
1$
#1565000
0$
#1570000
b10 &
1$
#1575000
0$
#1580000
b11 &
1$
#1585000
0$
#1590000
0!
b100 &
1$
#1595000
0$
#1600000
b101 &
1$
#1605000
0$
#1610000
b110 &
1$
#1615000
0$
#1620000
b0 &
1$
#1625000
0$
#1630000
1!
b1 &
1$
#1635000
0$
#1640000
b10 &
1$
#1645000
0$
#1650000
b11 &
1$
#1655000
0$
#1660000
b100 &
0!
1$
#1665000
0$
#1670000
b101 &
1$
#1675000
0$
#1680000
b110 &
1$
#1685000
0$
#1690000
b0 &
1$
#1695000
0$
#1700000
b1 &
1!
1$
#1705000
0$
#1710000
b10 &
1$
#1715000
0$
#1720000
b11 &
1$
#1725000
0$
#1730000
0!
b100 &
1$
#1735000
0$
#1740000
b101 &
1$
#1745000
0$
#1750000
b110 &
1$
#1755000
0$
#1760000
b0 &
1$
#1765000
0$
#1770000
1!
b1 &
1$
#1775000
0$
#1780000
b10 &
1$
#1785000
0$
#1790000
b11 &
1$
#1795000
0$
#1800000
b100 &
0!
1$
#1805000
0$
#1810000
b101 &
1$
#1815000
0$
#1820000
b110 &
1$
#1825000
0$
#1830000
b0 &
1$
#1835000
0$
#1840000
b1 &
1!
1$
#1845000
0$
#1850000
b10 &
1$
#1855000
0$
#1860000
b11 &
1$
#1865000
0$
#1870000
0!
b100 &
1$
#1875000
0$
#1880000
b101 &
1$
#1885000
0$
#1890000
b110 &
1$
#1895000
0$
#1900000
b0 &
1$
#1905000
0$
#1910000
1!
b1 &
1$
#1915000
0$
#1920000
b10 &
1$
#1925000
0$
#1930000
b11 &
1$
#1935000
0$
#1940000
b100 &
0!
1$
#1945000
0$
#1950000
b101 &
1$
#1955000
0$
#1960000
b110 &
1$
#1965000
0$
#1970000
b0 &
1$
#1975000
0$
#1980000
b1 &
1!
1$
#1985000
0$
#1990000
b10 &
1$
#1995000
0$
#2000000
b11 &
1$
